{
    "allowErrors": true,
    "customerKey": "8B6F4DE7-FA78-442B-8277-F5F0D3E576FB",
    "createdDate": "2022-05-16T05:36:16.403",
    "modifiedDate": "2022-05-16T06:40:21.777",
    "dateFormatLocale": "en-US",
    "deleteFile": false,
    "fieldMappings": [],
    "fieldMappingType": "InferFromColumnHeadings",
    "fileNamingPattern": "Data_Upload_16May.csv",
    "fileType": "CSV",
    "filter": "",
    "hasColumnHeader": true,
    "isOrderedImport": true,
    "isSequential": true,
    "maxFileAgeHours": 0,
    "maxImportFrequencyHours": 0,
    "maxFileAgeScheduleOffsetHours": 0,
    "name": "Kanika_Data_Upload_16May",
    "sendEmailNotification": false,
    "standardQuotedStrings": true,
    "fileTransferLocationTypeId": 0,
    "r__ftpLocation_name": "ExactTarget Enhanced FTP",
    "c__destinationType": "DataExtension",
    "r__dataExtension_CustomerKey": "35241807-2ED1-4048-801B-2E78D36D3575",
    "c__subscriberImportType": "DataExtension",
    "c__dataAction": "AddUpdate"
}
