{
    "allowErrors": true,
    "customerKey": "B99E9654-E074-41D4-A279-ED7FAF8D4458",
    "createdDate": "2021-08-13T00:56:46.107",
    "modifiedDate": "2021-08-13T00:56:46.107",
    "dateFormatLocale": "en-US",
    "deleteFile": false,
    "destinationObjectId": "1923151d-03fc-eb11-a306-48df37342cd0",
    "fieldMappings": [],
    "fieldMappingType": "InferFromColumnHeadings",
    "fileNamingPattern": "Ashwini_AutoJB.csv",
    "fileType": "CSV",
    "filter": "",
    "hasColumnHeader": true,
    "isOrderedImport": true,
    "isSequential": true,
    "maxFileAgeHours": 0,
    "maxImportFrequencyHours": 0,
    "maxFileAgeScheduleOffsetHours": 0,
    "name": "Ashwini_ImportFileToTriggerJB",
    "notificationEmailAddress": "ashwini.surwase@aethereus.com",
    "sendEmailNotification": true,
    "standardQuotedStrings": true,
    "fileTransferLocationTypeId": 0,
    "r__ftpLocation_name": "ExactTarget Enhanced FTP",
    "c__destinationType": "DataExtension",
    "c__subscriberImportType": "DataExtension",
    "c__dataAction": "AddUpdate"
}
