{
    "customerKey": "logo4",
    "assetType": {
        "name": "codesnippetblock",
        "displayName": "Code Snippet Block"
    },
    "fileProperties": {
        "fileName": "img_logo4"
    },
    "name": "img_logo4",
    "owner": {
        "email": "anushree.barapatre@aethereus.com",
        "name": "Anushree Barapatre"
    },
    "createdDate": "2022-06-07T06:04:38.837-06:00",
    "createdBy": {
        "email": "anushree.barapatre@aethereus.com",
        "name": "Anushree Barapatre"
    },
    "modifiedDate": "2022-06-07T06:04:41.36-06:00",
    "modifiedBy": {
        "email": "anushree.barapatre@aethereus.com",
        "name": "Anushree Barapatre"
    },
    "memberId": 514003648,
    "status": {
        "name": "Draft"
    },
    "availableViews": [],
    "modelVersion": 2,
    "r__folder_Path": "Content Builder/2021 Training/Anushree/Email"
}
