{
    "CustomerKey": "32E24D91-516A-43C9-9106-67380893BA45",
    "Name": "Customer_Product_Purchase_new",
    "Description": "",
    "IsSendable": true,
    "IsTestable": true,
    "SendableDataExtensionField": {
        "Name": "Customer_ID"
    },
    "SendableSubscriberField": {
        "Name": "Subscriber Key"
    },
    "RowBasedRetention": false,
    "ResetRetentionPeriodOnImport": false,
    "DeleteAtEndOfRetentionPeriod": false,
    "RetainUntil": "",
    "Fields": [
        {
            "Name": "Customer_ID",
            "DefaultValue": "",
            "MaxLength": 50,
            "IsRequired": true,
            "IsPrimaryKey": true,
            "FieldType": "Text"
        },
        {
            "Name": "Product_ID",
            "DefaultValue": "",
            "MaxLength": 50,
            "IsRequired": true,
            "IsPrimaryKey": true,
            "FieldType": "Text"
        },
        {
            "Name": "Quantity",
            "DefaultValue": "",
            "IsRequired": false,
            "IsPrimaryKey": false,
            "FieldType": "Number"
        }
    ],
    "r__folder_ContentType": "dataextension",
    "r__folder_Path": "Data Extensions/Practice - Kanika/Mango Republic"
}
