{
    "CustomerKey": "5BFFB4C1-9D32-4274-8BD3-5EFD50224BE4",
    "Name": "automate",
    "Description": "",
    "IsSendable": true,
    "IsTestable": true,
    "SendableDataExtensionField": {
        "Name": "Key"
    },
    "SendableSubscriberField": {
        "Name": "Subscriber Key"
    },
    "RowBasedRetention": false,
    "ResetRetentionPeriodOnImport": false,
    "DeleteAtEndOfRetentionPeriod": false,
    "RetainUntil": "",
    "Fields": [
        {
            "Name": "Name",
            "DefaultValue": "",
            "MaxLength": 50,
            "IsRequired": false,
            "IsPrimaryKey": false,
            "FieldType": "Text"
        },
        {
            "Name": "Key",
            "DefaultValue": "",
            "MaxLength": 50,
            "IsRequired": true,
            "IsPrimaryKey": true,
            "FieldType": "Text"
        },
        {
            "Name": "Email",
            "DefaultValue": "",
            "MaxLength": 254,
            "IsRequired": true,
            "IsPrimaryKey": false,
            "FieldType": "EmailAddress"
        },
        {
            "Name": "Age",
            "DefaultValue": "",
            "IsRequired": true,
            "IsPrimaryKey": false,
            "FieldType": "Number"
        }
    ],
    "r__folder_ContentType": "dataextension",
    "r__folder_Path": "Data Extensions/2022 Training/Abhinay"
}
