{
    "CustomerKey": "A40C1AB1-CA47-42F4-9BD8-2C93ED8F897C",
    "Name": "Insert_DE",
    "Description": "",
    "IsSendable": false,
    "IsTestable": false,
    "RowBasedRetention": false,
    "ResetRetentionPeriodOnImport": false,
    "DeleteAtEndOfRetentionPeriod": false,
    "RetainUntil": "",
    "Fields": [
        {
            "Name": "SubscriberKey",
            "DefaultValue": "",
            "MaxLength": 50,
            "IsRequired": true,
            "IsPrimaryKey": false,
            "FieldType": "Text"
        },
        {
            "Name": "JobID",
            "DefaultValue": "",
            "MaxLength": 50,
            "IsRequired": true,
            "IsPrimaryKey": false,
            "FieldType": "Text"
        },
        {
            "Name": "MessageType",
            "DefaultValue": "",
            "MaxLength": 50,
            "IsRequired": true,
            "IsPrimaryKey": false,
            "FieldType": "Text"
        },
        {
            "Name": "ProgramName",
            "DefaultValue": "",
            "MaxLength": 50,
            "IsRequired": true,
            "IsPrimaryKey": false,
            "FieldType": "Text"
        },
        {
            "Name": "EmailAddress",
            "DefaultValue": "",
            "MaxLength": 254,
            "IsRequired": true,
            "IsPrimaryKey": false,
            "FieldType": "EmailAddress"
        }
    ],
    "r__folder_ContentType": "dataextension",
    "r__folder_Path": "Data Extensions/2021 Training/Kavitha/AMP DE's"
}
