{
    "CustomerKey": "C904E425-B96B-49B6-85FB-37318F112800",
    "Name": "Anu_New_Cloudpage_Entry",
    "Description": "",
    "IsSendable": true,
    "IsTestable": false,
    "SendableDataExtensionField": {
        "Name": "Email"
    },
    "SendableSubscriberField": {
        "Name": "Subscriber Key"
    },
    "DataRetentionPeriodLength": 1,
    "DataRetentionPeriodUnitOfMeasure": 5,
    "RowBasedRetention": true,
    "ResetRetentionPeriodOnImport": false,
    "DeleteAtEndOfRetentionPeriod": false,
    "RetainUntil": "",
    "Fields": [
        {
            "Name": "First name",
            "DefaultValue": "",
            "MaxLength": 50,
            "IsRequired": true,
            "IsPrimaryKey": false,
            "FieldType": "Text"
        },
        {
            "Name": "Last name",
            "DefaultValue": "",
            "MaxLength": 50,
            "IsRequired": true,
            "IsPrimaryKey": false,
            "FieldType": "Text"
        },
        {
            "Name": "Email",
            "DefaultValue": "",
            "MaxLength": 254,
            "IsRequired": true,
            "IsPrimaryKey": true,
            "FieldType": "EmailAddress"
        }
    ],
    "r__folder_ContentType": "dataextension",
    "r__folder_Path": "Data Extensions/2021 Training/Anushree/Automation studio DE"
}
