{
    "CustomerKey": "CE0AD45D-F6B2-4098-8B10-54984D180DCC",
    "Name": "Customer_Behavior_Detail",
    "Description": "",
    "IsSendable": true,
    "IsTestable": false,
    "SendableDataExtensionField": {
        "Name": "Customer ID"
    },
    "SendableSubscriberField": {
        "Name": "Subscriber Key"
    },
    "DataRetentionPeriodLength": 2,
    "DataRetentionPeriodUnitOfMeasure": 5,
    "RowBasedRetention": true,
    "ResetRetentionPeriodOnImport": false,
    "DeleteAtEndOfRetentionPeriod": false,
    "RetainUntil": "",
    "Fields": [
        {
            "Name": "Customer ID",
            "DefaultValue": "",
            "MaxLength": 100,
            "IsRequired": true,
            "IsPrimaryKey": true,
            "FieldType": "Text"
        },
        {
            "Name": "Preference",
            "DefaultValue": "",
            "MaxLength": 50,
            "IsRequired": false,
            "IsPrimaryKey": false,
            "FieldType": "Text"
        },
        {
            "Name": "Buy",
            "DefaultValue": "True",
            "IsRequired": false,
            "IsPrimaryKey": false,
            "FieldType": "Boolean"
        }
    ],
    "r__folder_ContentType": "dataextension",
    "r__folder_Path": "Data Extensions/2021 Training/Anushree"
}
