{
    "CustomerKey": "F30D65DC-9596-41D2-A228-49E167A156ED",
    "Name": "Day3_VaccinationCustomerList",
    "Description": "",
    "IsSendable": true,
    "IsTestable": true,
    "SendableDataExtensionField": {
        "Name": "CustomerId"
    },
    "SendableSubscriberField": {
        "Name": "Subscriber Key"
    },
    "RowBasedRetention": false,
    "ResetRetentionPeriodOnImport": false,
    "DeleteAtEndOfRetentionPeriod": false,
    "RetainUntil": "",
    "Fields": [
        {
            "Name": "CustomerId",
            "DefaultValue": "",
            "MaxLength": 50,
            "IsRequired": false,
            "IsPrimaryKey": false,
            "FieldType": "Text"
        },
        {
            "Name": "EmailAddress",
            "DefaultValue": "",
            "MaxLength": 254,
            "IsRequired": false,
            "IsPrimaryKey": false,
            "FieldType": "EmailAddress"
        }
    ],
    "r__folder_ContentType": "dataextension",
    "r__folder_Path": "Data Extensions/2021 Training/Ashwini/AMPscript DE"
}
